LICENSE
README.md
setup.py
streamlit_app/__init__.py
streamlit_app/application.py
streamlit_app/errors.py
streamlit_app/page.py
streamlit_app/utils.py
streamlit_app.egg-info/PKG-INFO
streamlit_app.egg-info/SOURCES.txt
streamlit_app.egg-info/dependency_links.txt
streamlit_app.egg-info/requires.txt
streamlit_app.egg-info/top_level.txt