Metadata-Version: 2.1
Name: streamlit-app
Version: 0.0.3
Summary: A applet to use streamlit objectification
Home-page: https://github.com/ChangxingJiang/streamlit-app
Author: changxing
Author-email: 1278729001@qq.com
License: MIT License
Platform: all
Classifier: Intended Audience :: Developers
Classifier: Operating System :: OS Independent
Classifier: Natural Language :: Chinese (Simplified)
Classifier: Programming Language :: Python
Classifier: Programming Language :: Python :: 3.6
Classifier: Programming Language :: Python :: 3.7
Classifier: Programming Language :: Python :: 3.8
Classifier: Programming Language :: Python :: 3.9
Classifier: Programming Language :: Python :: 3.10
Classifier: Programming Language :: Python :: 3.11
Classifier: Programming Language :: Python :: 3.12
Classifier: Topic :: Software Development :: Libraries
License-File: LICENSE
Requires-Dist: streamlit
